openva_pipeline/__init__.py
openva_pipeline/dhis.py
openva_pipeline/exceptions.py
openva_pipeline/odk.py
openva_pipeline/openva.py
openva_pipeline/pipeline.py
openva_pipeline/run_pipeline.py
openva_pipeline/transfer_db.py
openva_pipeline/sql/pipelineDB.sql
openva_pipeline-0.99.dist-info/LICENSE
openva_pipeline-0.99.dist-info/METADATA
openva_pipeline-0.99.dist-info/WHEEL
openva_pipeline-0.99.dist-info/top_level.txt
openva_pipeline-0.99.dist-info/RECORD
