Metadata-Version: 2.1
Name: openva-pipeline
Version: 0.99
Summary: Automate the processing of verbal autopsy data
Author: Jason Thomas, Samuel J. Clark, Martin W. Bratschi
Maintainer-email: Jason Thomas <jarathomas@gmail.com>
Project-URL: Homepage, https://github.com/verbal-autopsy-software/openva_pipeline
Project-URL: Bug Tracker, https://github.com/verbal-autopsy-software/openva_pipeline/issues
Classifier: Programming Language :: Python :: 3
Classifier: Programming Language :: Python :: 3.8
Classifier: Programming Language :: Python :: 3.9
Classifier: Programming Language :: Python :: 3.10
Classifier: Programming Language :: Python :: 3.11
Classifier: License :: OSI Approved :: GNU General Public License v3 (GPLv3)
Classifier: Operating System :: POSIX :: Linux
Requires-Python: >=3.8
License-File: LICENSE
Requires-Dist: pandas
Requires-Dist: sqlcipher3
Requires-Dist: requests
Requires-Dist: pycrossva >=0.97
